naurok/__init__.py
naurok/client.py
naurok/req.py
naurok.py-1.0.dist-info/LICENSE
naurok.py-1.0.dist-info/METADATA
naurok.py-1.0.dist-info/WHEEL
naurok.py-1.0.dist-info/top_level.txt
naurok.py-1.0.dist-info/RECORD
